wcwidth-stubs/__init__.py
wcwidth-stubs/py.typed
wcwidth_stubs-0.3.0.1.dist-info/WHEEL
wcwidth_stubs-0.3.0.1.dist-info/METADATA
wcwidth_stubs-0.3.0.1.dist-info/RECORD
