Metadata-Version: 2.4
Name: wcwidth-stubs
Version: 0.3.0.1
Summary: typing stubs for wcwidth
Author-email: trim21 <trim21.me@gmail.com>
Requires-Python: >=3.8
Requires-Dist: wcwidth>=0.3.0,<1
Project-URL: repository, https://github.com/trim21/wcwidth-stubs
